fastapi_tj_tpauth_jwt/__init__.py
fastapi_tj_tpauth_jwt/jwt_utils.py
fastapi_tj_tpauth_jwt/tpauth_jwt.py
fastapi_tj_tpauth_jwt-1.0.0.dist-info/LICENSE
fastapi_tj_tpauth_jwt-1.0.0.dist-info/METADATA
fastapi_tj_tpauth_jwt-1.0.0.dist-info/WHEEL
fastapi_tj_tpauth_jwt-1.0.0.dist-info/RECORD
