Metadata-Version: 2.1
Name: fastapi-tj-tpauth-jwt
Version: 1.0.0
Summary: Integrate JWT into FastAPI using TP Servers authentication.
Home-page: https://github.com/duynguyen02/fastapi-tj-tpauth-jwt
Author: Duy Nguyen
Author-email: duynguyen02.dev@gmail.com
Requires-Python: >=3.9,<4.0
Classifier: Programming Language :: Python :: 3
Classifier: Programming Language :: Python :: 3.9
Classifier: Programming Language :: Python :: 3.10
Classifier: Programming Language :: Python :: 3.11
Classifier: Programming Language :: Python :: 3.12
Requires-Dist: fastapi[standard] (>=0.115.2,<0.116.0)
Requires-Dist: pydantic (>=2.9.2,<3.0.0)
Requires-Dist: pyjwt (>=2.9.0,<3.0.0)
Requires-Dist: tj-tpauth (>=1.1.0,<2.0.0)
Project-URL: Repository, https://github.com/duynguyen02/fastapi-tj-tpauth-jwt
